{"images": [{"file_name": "228.bmp", "height": 128, "width": 128, "id": 1}, {"file_name": "1363.bmp", "height": 128, "width": 128, "id": 2}, {"file_name": "906.bmp", "height": 128, "width": 128, "id": 4}, {"file_name": "1832.bmp", "height": 128, "width": 128, "id": 5}, {"file_name": "1136.bmp", "height": 128, "width": 128, "id": 6}, {"file_name": "1015.bmp", "height": 128, "width": 128, "id": 7}, {"file_name": "096.bmp", "height": 128, "width": 128, "id": 8}, {"file_name": "312.bmp", "height": 128, "width": 128, "id": 9}, {"file_name": "389.bmp", "height": 128, "width": 128, "id": 10}, {"file_name": "783.bmp", "height": 128, "width": 128, "id": 11}, {"file_name": "973.bmp", "height": 128, "width": 128, "id": 12}, {"file_name": "062.bmp", "height": 128, "width": 128, "id": 13}, {"file_name": "1390.bmp", "height": 128, "width": 128, "id": 14}, {"file_name": "219.bmp", "height": 128, "width": 128, "id": 15}, {"file_name": "578.bmp", "height": 128, "width": 128, "id": 16}, {"file_name": "1582.bmp", "height": 128, "width": 128, "id": 17}, {"file_name": "722.bmp", "height": 128, "width": 128, "id": 20}, {"file_name": "1719.bmp", "height": 128, "width": 128, "id": 21}, {"file_name": "843.bmp", "height": 128, "width": 128, "id": 22}, {"file_name": "1440.bmp", "height": 128, "width": 128, "id": 25}, {"file_name": "1483.bmp", "height": 128, "width": 128, "id": 26}, {"file_name": "1405.bmp", "height": 128, "width": 128, "id": 28}, {"file_name": "104.bmp", "height": 128, "width": 128, "id": 29}, {"file_name": "1101.bmp", "height": 128, "width": 128, "id": 30}, {"file_name": "1083.bmp", "height": 128, "width": 128, "id": 31}, {"file_name": "1706.bmp", "height": 128, "width": 128, "id": 32}, {"file_name": "347.bmp", "height": 128, "width": 128, "id": 33}, {"file_name": "750.bmp", "height": 128, "width": 128, "id": 35}, {"file_name": "884.bmp", "height": 128, "width": 128, "id": 36}, {"file_name": "778.bmp", "height": 128, "width": 128, "id": 38}, {"file_name": "523.bmp", "height": 128, "width": 128, "id": 39}, {"file_name": "846.bmp", "height": 128, "width": 128, "id": 40}, {"file_name": "509.bmp", "height": 128, "width": 128, "id": 41}, {"file_name": "1107.bmp", "height": 128, "width": 128, "id": 43}, {"file_name": "1616.bmp", "height": 128, "width": 128, "id": 44}, {"file_name": "1224.bmp", "height": 128, "width": 128, "id": 45}, {"file_name": "870.bmp", "height": 128, "width": 128, "id": 46}, {"file_name": "902.bmp", "height": 128, "width": 128, "id": 47}, {"file_name": "185.bmp", "height": 128, "width": 128, "id": 48}, {"file_name": "565.bmp", "height": 128, "width": 128, "id": 49}, {"file_name": "1655.bmp", "height": 128, "width": 128, "id": 52}, {"file_name": "1414.bmp", "height": 128, "width": 128, "id": 53}, {"file_name": "051.bmp", "height": 128, "width": 128, "id": 55}, {"file_name": "575.bmp", "height": 128, "width": 128, "id": 56}, {"file_name": "1577.bmp", "height": 128, "width": 128, "id": 59}, {"file_name": "244.bmp", "height": 128, "width": 128, "id": 60}, {"file_name": "195.bmp", "height": 128, "width": 128, "id": 61}, {"file_name": "469.bmp", "height": 128, "width": 128, "id": 62}, {"file_name": "1909.bmp", "height": 128, "width": 128, "id": 64}, {"file_name": "1383.bmp", "height": 128, "width": 128, "id": 65}, {"file_name": "1635.bmp", "height": 128, "width": 128, "id": 66}, {"file_name": "229.bmp", "height": 128, "width": 128, "id": 69}, {"file_name": "1199.bmp", "height": 128, "width": 128, "id": 70}, {"file_name": "1379.bmp", "height": 128, "width": 128, "id": 71}, {"file_name": "689.bmp", "height": 128, "width": 128, "id": 72}, {"file_name": "1925.bmp", "height": 128, "width": 128, "id": 73}, {"file_name": "1362.bmp", "height": 128, "width": 128, "id": 74}, {"file_name": "393.bmp", "height": 128, "width": 128, "id": 76}, {"file_name": "311.bmp", "height": 128, "width": 128, "id": 77}, {"file_name": "1060.bmp", "height": 128, "width": 128, "id": 78}, {"file_name": "068.bmp", "height": 128, "width": 128, "id": 79}, {"file_name": "579.bmp", "height": 128, "width": 128, "id": 80}, {"file_name": "414.bmp", "height": 128, "width": 128, "id": 81}, {"file_name": "845.bmp", "height": 128, "width": 128, "id": 82}, {"file_name": "424.bmp", "height": 128, "width": 128, "id": 83}, {"file_name": "369.bmp", "height": 128, "width": 128, "id": 84}, {"file_name": "1138.bmp", "height": 128, "width": 128, "id": 85}, {"file_name": "402.bmp", "height": 128, "width": 128, "id": 86}, {"file_name": "1389.bmp", "height": 128, "width": 128, "id": 87}, {"file_name": "1626.bmp", "height": 128, "width": 128, "id": 88}, {"file_name": "932.bmp", "height": 128, "width": 128, "id": 89}, {"file_name": "877.bmp", "height": 128, "width": 128, "id": 91}, {"file_name": "109.bmp", "height": 128, "width": 128, "id": 92}, {"file_name": "1273.bmp", "height": 128, "width": 128, "id": 95}, {"file_name": "561.bmp", "height": 128, "width": 128, "id": 97}, {"file_name": "1664.bmp", "height": 128, "width": 128, "id": 98}, {"file_name": "1166.bmp", "height": 128, "width": 128, "id": 100}, {"file_name": "990.bmp", "height": 128, "width": 128, "id": 101}, {"file_name": "1857.bmp", "height": 128, "width": 128, "id": 102}, {"file_name": "927.bmp", "height": 128, "width": 128, "id": 103}, {"file_name": "922.bmp", "height": 128, "width": 128, "id": 104}, {"file_name": "836.bmp", "height": 128, "width": 128, "id": 105}, {"file_name": "457.bmp", "height": 128, "width": 128, "id": 106}, {"file_name": "1639.bmp", "height": 128, "width": 128, "id": 108}, {"file_name": "851.bmp", "height": 128, "width": 128, "id": 109}, {"file_name": "482.bmp", "height": 128, "width": 128, "id": 110}, {"file_name": "1133.bmp", "height": 128, "width": 128, "id": 112}, {"file_name": "1710.bmp", "height": 128, "width": 128, "id": 113}, {"file_name": "675.bmp", "height": 128, "width": 128, "id": 114}, {"file_name": "323.bmp", "height": 128, "width": 128, "id": 115}, {"file_name": "652.bmp", "height": 128, "width": 128, "id": 116}, {"file_name": "1894.bmp", "height": 128, "width": 128, "id": 117}, {"file_name": "470.bmp", "height": 128, "width": 128, "id": 118}, {"file_name": "416.bmp", "height": 128, "width": 128, "id": 119}, {"file_name": "093.bmp", "height": 128, "width": 128, "id": 120}, {"file_name": "1737.bmp", "height": 128, "width": 128, "id": 121}, {"file_name": "1685.bmp", "height": 128, "width": 128, "id": 122}, {"file_name": "1188.bmp", "height": 128, "width": 128, "id": 124}, {"file_name": "1711.bmp", "height": 128, "width": 128, "id": 125}, {"file_name": "1407.bmp", "height": 128, "width": 128, "id": 126}, {"file_name": "1478.bmp", "height": 128, "width": 128, "id": 127}, {"file_name": "1541.bmp", "height": 128, "width": 128, "id": 128}, {"file_name": "223.bmp", "height": 128, "width": 128, "id": 129}, {"file_name": "793.bmp", "height": 128, "width": 128, "id": 130}, {"file_name": "358.bmp", "height": 128, "width": 128, "id": 131}, {"file_name": "1600.bmp", "height": 128, "width": 128, "id": 132}, {"file_name": "1409.bmp", "height": 128, "width": 128, "id": 133}, {"file_name": "980.bmp", "height": 128, "width": 128, "id": 134}, {"file_name": "352.bmp", "height": 128, "width": 128, "id": 135}, {"file_name": "820.bmp", "height": 128, "width": 128, "id": 136}, {"file_name": "1175.bmp", "height": 128, "width": 128, "id": 137}, {"file_name": "1433.bmp", "height": 128, "width": 128, "id": 138}, {"file_name": "1849.bmp", "height": 128, "width": 128, "id": 139}, {"file_name": "1862.bmp", "height": 128, "width": 128, "id": 140}, {"file_name": "1638.bmp", "height": 128, "width": 128, "id": 141}, {"file_name": "998.bmp", "height": 128, "width": 128, "id": 142}, {"file_name": "1507.bmp", "height": 128, "width": 128, "id": 143}, {"file_name": "642.bmp", "height": 128, "width": 128, "id": 144}, {"file_name": "1026.bmp", "height": 128, "width": 128, "id": 145}, {"file_name": "996.bmp", "height": 128, "width": 128, "id": 146}, {"file_name": "1388.bmp", "height": 128, "width": 128, "id": 147}, {"file_name": "674.bmp", "height": 128, "width": 128, "id": 148}, {"file_name": "1033.bmp", "height": 128, "width": 128, "id": 149}, {"file_name": "1223.bmp", "height": 128, "width": 128, "id": 150}, {"file_name": "1444.bmp", "height": 128, "width": 128, "id": 151}, {"file_name": "313.bmp", "height": 128, "width": 128, "id": 153}, {"file_name": "944.bmp", "height": 128, "width": 128, "id": 154}, {"file_name": "615.bmp", "height": 128, "width": 128, "id": 155}, {"file_name": "1375.bmp", "height": 128, "width": 128, "id": 156}, {"file_name": "1419.bmp", "height": 128, "width": 128, "id": 157}, {"file_name": "1473.bmp", "height": 128, "width": 128, "id": 158}, {"file_name": "1358.bmp", "height": 128, "width": 128, "id": 159}, {"file_name": "1517.bmp", "height": 128, "width": 128, "id": 160}, {"file_name": "148.bmp", "height": 128, "width": 128, "id": 162}, {"file_name": "316.bmp", "height": 128, "width": 128, "id": 163}, {"file_name": "1846.bmp", "height": 128, "width": 128, "id": 164}, {"file_name": "664.bmp", "height": 128, "width": 128, "id": 165}, {"file_name": "1431.bmp", "height": 128, "width": 128, "id": 167}, {"file_name": "082.bmp", "height": 128, "width": 128, "id": 168}, {"file_name": "479.bmp", "height": 128, "width": 128, "id": 169}, {"file_name": "1595.bmp", "height": 128, "width": 128, "id": 170}, {"file_name": "1731.bmp", "height": 128, "width": 128, "id": 171}, {"file_name": "188.bmp", "height": 128, "width": 128, "id": 172}, {"file_name": "274.bmp", "height": 128, "width": 128, "id": 173}, {"file_name": "1516.bmp", "height": 128, "width": 128, "id": 174}, {"file_name": "433.bmp", "height": 128, "width": 128, "id": 175}, {"file_name": "233.bmp", "height": 128, "width": 128, "id": 176}, {"file_name": "1724.bmp", "height": 128, "width": 128, "id": 177}, {"file_name": "905.bmp", "height": 128, "width": 128, "id": 179}, {"file_name": "1202.bmp", "height": 128, "width": 128, "id": 180}, {"file_name": "831.bmp", "height": 128, "width": 128, "id": 181}, {"file_name": "1123.bmp", "height": 128, "width": 128, "id": 182}, {"file_name": "359.bmp", "height": 128, "width": 128, "id": 183}, {"file_name": "1474.bmp", "height": 128, "width": 128, "id": 184}, {"file_name": "1867.bmp", "height": 128, "width": 128, "id": 185}, {"file_name": "604.bmp", "height": 128, "width": 128, "id": 186}, {"file_name": "602.bmp", "height": 128, "width": 128, "id": 187}, {"file_name": "933.bmp", "height": 128, "width": 128, "id": 189}, {"file_name": "1144.bmp", "height": 128, "width": 128, "id": 190}, {"file_name": "1127.bmp", "height": 128, "width": 128, "id": 191}, {"file_name": "1718.bmp", "height": 128, "width": 128, "id": 193}, {"file_name": "526.bmp", "height": 128, "width": 128, "id": 194}, {"file_name": "1694.bmp", "height": 128, "width": 128, "id": 195}, {"file_name": "716.bmp", "height": 128, "width": 128, "id": 197}, {"file_name": "097.bmp", "height": 128, "width": 128, "id": 202}, {"file_name": "1196.bmp", "height": 128, "width": 128, "id": 204}, {"file_name": "1692.bmp", "height": 128, "width": 128, "id": 205}, {"file_name": "318.bmp", "height": 128, "width": 128, "id": 206}, {"file_name": "320.bmp", "height": 128, "width": 128, "id": 207}, {"file_name": "1620.bmp", "height": 128, "width": 128, "id": 208}, {"file_name": "1721.bmp", "height": 128, "width": 128, "id": 209}, {"file_name": "021.bmp", "height": 128, "width": 128, "id": 210}, {"file_name": "1332.bmp", "height": 128, "width": 128, "id": 212}, {"file_name": "896.bmp", "height": 128, "width": 128, "id": 213}, {"file_name": "1293.bmp", "height": 128, "width": 128, "id": 214}, {"file_name": "1051.bmp", "height": 128, "width": 128, "id": 215}, {"file_name": "838.bmp", "height": 128, "width": 128, "id": 216}, {"file_name": "654.bmp", "height": 128, "width": 128, "id": 217}, {"file_name": "942.bmp", "height": 128, "width": 128, "id": 218}, {"file_name": "074.bmp", "height": 128, "width": 128, "id": 219}, {"file_name": "1807.bmp", "height": 128, "width": 128, "id": 220}, {"file_name": "1179.bmp", "height": 128, "width": 128, "id": 222}, {"file_name": "194.bmp", "height": 128, "width": 128, "id": 223}, {"file_name": "1132.bmp", "height": 128, "width": 128, "id": 224}, {"file_name": "119.bmp", "height": 128, "width": 128, "id": 225}, {"file_name": "1864.bmp", "height": 128, "width": 128, "id": 227}, {"file_name": "1654.bmp", "height": 128, "width": 128, "id": 228}, {"file_name": "698.bmp", "height": 128, "width": 128, "id": 231}, {"file_name": "882.bmp", "height": 128, "width": 128, "id": 232}, {"file_name": "1445.bmp", "height": 128, "width": 128, "id": 233}, {"file_name": "1805.bmp", "height": 128, "width": 128, "id": 234}, {"file_name": "544.bmp", "height": 128, "width": 128, "id": 235}, {"file_name": "1830.bmp", "height": 128, "width": 128, "id": 236}, {"file_name": "633.bmp", "height": 128, "width": 128, "id": 238}, {"file_name": "1120.bmp", "height": 128, "width": 128, "id": 239}, {"file_name": "1787.bmp", "height": 128, "width": 128, "id": 240}, {"file_name": "1645.bmp", "height": 128, "width": 128, "id": 242}, {"file_name": "504.bmp", "height": 128, "width": 128, "id": 243}, {"file_name": "754.bmp", "height": 128, "width": 128, "id": 244}, {"file_name": "1495.bmp", "height": 128, "width": 128, "id": 245}, {"file_name": "124.bmp", "height": 128, "width": 128, "id": 246}, {"file_name": "1263.bmp", "height": 128, "width": 128, "id": 247}, {"file_name": "034.bmp", "height": 128, "width": 128, "id": 248}, {"file_name": "1274.bmp", "height": 128, "width": 128, "id": 249}, {"file_name": "1859.bmp", "height": 128, "width": 128, "id": 250}, {"file_name": "045.bmp", "height": 128, "width": 128, "id": 251}, {"file_name": "1803.bmp", "height": 128, "width": 128, "id": 252}, {"file_name": "1568.bmp", "height": 128, "width": 128, "id": 253}, {"file_name": "1660.bmp", "height": 128, "width": 128, "id": 254}, {"file_name": "125.bmp", "height": 128, "width": 128, "id": 255}, {"file_name": "800.bmp", "height": 128, "width": 128, "id": 256}, {"file_name": "1349.bmp", "height": 128, "width": 128, "id": 257}, {"file_name": "726.bmp", "height": 128, "width": 128, "id": 258}, {"file_name": "1309.bmp", "height": 128, "width": 128, "id": 259}, {"file_name": "314.bmp", "height": 128, "width": 128, "id": 260}, {"file_name": "849.bmp", "height": 128, "width": 128, "id": 261}, {"file_name": "101.bmp", "height": 128, "width": 128, "id": 262}, {"file_name": "1018.bmp", "height": 128, "width": 128, "id": 264}, {"file_name": "963.bmp", "height": 128, "width": 128, "id": 265}, {"file_name": "353.bmp", "height": 128, "width": 128, "id": 266}, {"file_name": "1627.bmp", "height": 128, "width": 128, "id": 267}, {"file_name": "1153.bmp", "height": 128, "width": 128, "id": 268}, {"file_name": "081.bmp", "height": 128, "width": 128, "id": 269}, {"file_name": "1312.bmp", "height": 128, "width": 128, "id": 270}, {"file_name": "1780.bmp", "height": 128, "width": 128, "id": 271}, {"file_name": "214.bmp", "height": 128, "width": 128, "id": 272}, {"file_name": "1879.bmp", "height": 128, "width": 128, "id": 274}, {"file_name": "1452.bmp", "height": 128, "width": 128, "id": 275}, {"file_name": "920.bmp", "height": 128, "width": 128, "id": 276}, {"file_name": "857.bmp", "height": 128, "width": 128, "id": 279}, {"file_name": "492.bmp", "height": 128, "width": 128, "id": 280}, {"file_name": "1567.bmp", "height": 128, "width": 128, "id": 281}, {"file_name": "156.bmp", "height": 128, "width": 128, "id": 283}, {"file_name": "1677.bmp", "height": 128, "width": 128, "id": 284}, {"file_name": "120.bmp", "height": 128, "width": 128, "id": 285}, {"file_name": "362.bmp", "height": 128, "width": 128, "id": 286}, {"file_name": "656.bmp", "height": 128, "width": 128, "id": 287}, {"file_name": "1075.bmp", "height": 128, "width": 128, "id": 289}, {"file_name": "276.bmp", "height": 128, "width": 128, "id": 292}, {"file_name": "1351.bmp", "height": 128, "width": 128, "id": 294}, {"file_name": "1027.bmp", "height": 128, "width": 128, "id": 295}, {"file_name": "495.bmp", "height": 128, "width": 128, "id": 296}, {"file_name": "206.bmp", "height": 128, "width": 128, "id": 297}, {"file_name": "1090.bmp", "height": 128, "width": 128, "id": 299}, {"file_name": "892.bmp", "height": 128, "width": 128, "id": 300}, {"file_name": "1818.bmp", "height": 128, "width": 128, "id": 301}, {"file_name": "182.bmp", "height": 128, "width": 128, "id": 302}, {"file_name": "1373.bmp", "height": 128, "width": 128, "id": 303}, {"file_name": "053.bmp", "height": 128, "width": 128, "id": 304}, {"file_name": "981.bmp", "height": 128, "width": 128, "id": 305}, {"file_name": "1459.bmp", "height": 128, "width": 128, "id": 306}, {"file_name": "485.bmp", "height": 128, "width": 128, "id": 307}, {"file_name": "1361.bmp", "height": 128, "width": 128, "id": 308}, {"file_name": "869.bmp", "height": 128, "width": 128, "id": 309}, {"file_name": "881.bmp", "height": 128, "width": 128, "id": 310}, {"file_name": "678.bmp", "height": 128, "width": 128, "id": 311}, {"file_name": "1394.bmp", "height": 128, "width": 128, "id": 312}, {"file_name": "863.bmp", "height": 128, "width": 128, "id": 313}, {"file_name": "023.bmp", "height": 128, "width": 128, "id": 314}, {"file_name": "573.bmp", "height": 128, "width": 128, "id": 316}, {"file_name": "044.bmp", "height": 128, "width": 128, "id": 317}, {"file_name": "1670.bmp", "height": 128, "width": 128, "id": 318}, {"file_name": "681.bmp", "height": 128, "width": 128, "id": 319}, {"file_name": "1253.bmp", "height": 128, "width": 128, "id": 320}, {"file_name": "1292.bmp", "height": 128, "width": 128, "id": 322}, {"file_name": "1618.bmp", "height": 128, "width": 128, "id": 323}, {"file_name": "1477.bmp", "height": 128, "width": 128, "id": 325}, {"file_name": "1225.bmp", "height": 128, "width": 128, "id": 326}, {"file_name": "771.bmp", "height": 128, "width": 128, "id": 327}, {"file_name": "627.bmp", "height": 128, "width": 128, "id": 328}, {"file_name": "047.bmp", "height": 128, "width": 128, "id": 332}, {"file_name": "226.bmp", "height": 128, "width": 128, "id": 333}, {"file_name": "301.bmp", "height": 128, "width": 128, "id": 334}, {"file_name": "992.bmp", "height": 128, "width": 128, "id": 335}, {"file_name": "1147.bmp", "height": 128, "width": 128, "id": 336}, {"file_name": "577.bmp", "height": 128, "width": 128, "id": 338}, {"file_name": "1679.bmp", "height": 128, "width": 128, "id": 339}, {"file_name": "199.bmp", "height": 128, "width": 128, "id": 341}, {"file_name": "970.bmp", "height": 128, "width": 128, "id": 342}, {"file_name": "816.bmp", "height": 128, "width": 128, "id": 343}, {"file_name": "003.bmp", "height": 128, "width": 128, "id": 345}, {"file_name": "307.bmp", "height": 128, "width": 128, "id": 346}, {"file_name": "1528.bmp", "height": 128, "width": 128, "id": 348}, {"file_name": "1596.bmp", "height": 128, "width": 128, "id": 349}, {"file_name": "496.bmp", "height": 128, "width": 128, "id": 350}, {"file_name": "670.bmp", "height": 128, "width": 128, "id": 351}, {"file_name": "1422.bmp", "height": 128, "width": 128, "id": 352}, {"file_name": "016.bmp", "height": 128, "width": 128, "id": 353}, {"file_name": "383.bmp", "height": 128, "width": 128, "id": 354}, {"file_name": "1399.bmp", "height": 128, "width": 128, "id": 355}, {"file_name": "1424.bmp", "height": 128, "width": 128, "id": 356}, {"file_name": "1531.bmp", "height": 128, "width": 128, "id": 357}, {"file_name": "761.bmp", "height": 128, "width": 128, "id": 358}, {"file_name": "1821.bmp", "height": 128, "width": 128, "id": 359}, {"file_name": "1688.bmp", "height": 128, "width": 128, "id": 360}, {"file_name": "174.bmp", "height": 128, "width": 128, "id": 362}, {"file_name": "269.bmp", "height": 128, "width": 128, "id": 363}, {"file_name": "275.bmp", "height": 128, "width": 128, "id": 365}, {"file_name": "1689.bmp", "height": 128, "width": 128, "id": 366}, {"file_name": "1793.bmp", "height": 128, "width": 128, "id": 367}, {"file_name": "1823.bmp", "height": 128, "width": 128, "id": 369}, {"file_name": "1372.bmp", "height": 128, "width": 128, "id": 371}, {"file_name": "741.bmp", "height": 128, "width": 128, "id": 372}, {"file_name": "1021.bmp", "height": 128, "width": 128, "id": 373}, {"file_name": "911.bmp", "height": 128, "width": 128, "id": 374}, {"file_name": "560.bmp", "height": 128, "width": 128, "id": 375}, {"file_name": "619.bmp", "height": 128, "width": 128, "id": 376}, {"file_name": "215.bmp", "height": 128, "width": 128, "id": 378}, {"file_name": "694.bmp", "height": 128, "width": 128, "id": 379}, {"file_name": "745.bmp", "height": 128, "width": 128, "id": 381}, {"file_name": "085.bmp", "height": 128, "width": 128, "id": 382}, {"file_name": "1597.bmp", "height": 128, "width": 128, "id": 383}, {"file_name": "1157.bmp", "height": 128, "width": 128, "id": 384}, {"file_name": "1702.bmp", "height": 128, "width": 128, "id": 386}, {"file_name": "1588.bmp", "height": 128, "width": 128, "id": 387}, {"file_name": "1063.bmp", "height": 128, "width": 128, "id": 388}, {"file_name": "1210.bmp", "height": 128, "width": 128, "id": 389}, {"file_name": "170.bmp", "height": 128, "width": 128, "id": 390}, {"file_name": "298.bmp", "height": 128, "width": 128, "id": 391}, {"file_name": "1492.bmp", "height": 128, "width": 128, "id": 392}, {"file_name": "1594.bmp", "height": 128, "width": 128, "id": 393}, {"file_name": "1032.bmp", "height": 128, "width": 128, "id": 394}, {"file_name": "1230.bmp", "height": 128, "width": 128, "id": 395}, {"file_name": "812.bmp", "height": 128, "width": 128, "id": 396}, {"file_name": "167.bmp", "height": 128, "width": 128, "id": 397}, {"file_name": "507.bmp", "height": 128, "width": 128, "id": 398}, {"file_name": "1453.bmp", "height": 128, "width": 128, "id": 399}, {"file_name": "1833.bmp", "height": 128, "width": 128, "id": 404}, {"file_name": "333.bmp", "height": 128, "width": 128, "id": 405}, {"file_name": "1221.bmp", "height": 128, "width": 128, "id": 406}, {"file_name": "399.bmp", "height": 128, "width": 128, "id": 407}, {"file_name": "1045.bmp", "height": 128, "width": 128, "id": 409}, {"file_name": "1169.bmp", "height": 128, "width": 128, "id": 411}, {"file_name": "1844.bmp", "height": 128, "width": 128, "id": 412}, {"file_name": "959.bmp", "height": 128, "width": 128, "id": 414}, {"file_name": "443.bmp", "height": 128, "width": 128, "id": 416}, {"file_name": "281.bmp", "height": 128, "width": 128, "id": 418}, {"file_name": "257.bmp", "height": 128, "width": 128, "id": 419}, {"file_name": "179.bmp", "height": 128, "width": 128, "id": 420}, {"file_name": "203.bmp", "height": 128, "width": 128, "id": 421}, {"file_name": "946.bmp", "height": 128, "width": 128, "id": 422}, {"file_name": "1284.bmp", "height": 128, "width": 128, "id": 423}, {"file_name": "1423.bmp", "height": 128, "width": 128, "id": 424}, {"file_name": "1911.bmp", "height": 128, "width": 128, "id": 425}, {"file_name": "108.bmp", "height": 128, "width": 128, "id": 426}, {"file_name": "1791.bmp", "height": 128, "width": 128, "id": 428}, {"file_name": "1843.bmp", "height": 128, "width": 128, "id": 429}, {"file_name": "1717.bmp", "height": 128, "width": 128, "id": 430}, {"file_name": "1611.bmp", "height": 128, "width": 128, "id": 431}, {"file_name": "1403.bmp", "height": 128, "width": 128, "id": 433}, {"file_name": "715.bmp", "height": 128, "width": 128, "id": 434}, {"file_name": "1699.bmp", "height": 128, "width": 128, "id": 435}, {"file_name": "1356.bmp", "height": 128, "width": 128, "id": 438}, {"file_name": "878.bmp", "height": 128, "width": 128, "id": 439}, {"file_name": "1491.bmp", "height": 128, "width": 128, "id": 440}, {"file_name": "1794.bmp", "height": 128, "width": 128, "id": 442}, {"file_name": "1559.bmp", "height": 128, "width": 128, "id": 443}, {"file_name": "1080.bmp", "height": 128, "width": 128, "id": 444}, {"file_name": "1192.bmp", "height": 128, "width": 128, "id": 445}, {"file_name": "168.bmp", "height": 128, "width": 128, "id": 446}, {"file_name": "163.bmp", "height": 128, "width": 128, "id": 447}, {"file_name": "471.bmp", "height": 128, "width": 128, "id": 448}, {"file_name": "155.bmp", "height": 128, "width": 128, "id": 449}, {"file_name": "1270.bmp", "height": 128, "width": 128, "id": 450}, {"file_name": "1921.bmp", "height": 128, "width": 128, "id": 451}, {"file_name": "285.bmp", "height": 128, "width": 128, "id": 452}, {"file_name": "663.bmp", "height": 128, "width": 128, "id": 454}, {"file_name": "1067.bmp", "height": 128, "width": 128, "id": 455}, {"file_name": "1892.bmp", "height": 128, "width": 128, "id": 456}, {"file_name": "1117.bmp", "height": 128, "width": 128, "id": 457}, {"file_name": "1089.bmp", "height": 128, "width": 128, "id": 458}, {"file_name": "251.bmp", "height": 128, "width": 128, "id": 459}, {"file_name": "957.bmp", "height": 128, "width": 128, "id": 461}, {"file_name": "723.bmp", "height": 128, "width": 128, "id": 462}, {"file_name": "1443.bmp", "height": 128, "width": 128, "id": 463}, {"file_name": "951.bmp", "height": 128, "width": 128, "id": 464}, {"file_name": "446.bmp", "height": 128, "width": 128, "id": 465}, {"file_name": "1371.bmp", "height": 128, "width": 128, "id": 466}, {"file_name": "494.bmp", "height": 128, "width": 128, "id": 467}, {"file_name": "438.bmp", "height": 128, "width": 128, "id": 468}, {"file_name": "1416.bmp", "height": 128, "width": 128, "id": 469}, {"file_name": "340.bmp", "height": 128, "width": 128, "id": 470}, {"file_name": "1772.bmp", "height": 128, "width": 128, "id": 471}, {"file_name": "1913.bmp", "height": 128, "width": 128, "id": 472}, {"file_name": "501.bmp", "height": 128, "width": 128, "id": 474}, {"file_name": "222.bmp", "height": 128, "width": 128, "id": 477}, {"file_name": "487.bmp", "height": 128, "width": 128, "id": 478}, {"file_name": "1502.bmp", "height": 128, "width": 128, "id": 479}, {"file_name": "376.bmp", "height": 128, "width": 128, "id": 480}, {"file_name": "071.bmp", "height": 128, "width": 128, "id": 482}, {"file_name": "1493.bmp", "height": 128, "width": 128, "id": 483}, {"file_name": "581.bmp", "height": 128, "width": 128, "id": 484}, {"file_name": "305.bmp", "height": 128, "width": 128, "id": 485}, {"file_name": "232.bmp", "height": 128, "width": 128, "id": 487}, {"file_name": "1748.bmp", "height": 128, "width": 128, "id": 488}, {"file_name": "975.bmp", "height": 128, "width": 128, "id": 489}, {"file_name": "583.bmp", "height": 128, "width": 128, "id": 491}, {"file_name": "1214.bmp", "height": 128, "width": 128, "id": 493}, {"file_name": "112.bmp", "height": 128, "width": 128, "id": 494}, {"file_name": "183.bmp", "height": 128, "width": 128, "id": 495}, {"file_name": "719.bmp", "height": 128, "width": 128, "id": 496}, {"file_name": "1217.bmp", "height": 128, "width": 128, "id": 497}, {"file_name": "1662.bmp", "height": 128, "width": 128, "id": 499}, {"file_name": "080.bmp", "height": 128, "width": 128, "id": 500}, {"file_name": "026.bmp", "height": 128, "width": 128, "id": 501}, {"file_name": "895.bmp", "height": 128, "width": 128, "id": 502}, {"file_name": "280.bmp", "height": 128, "width": 128, "id": 503}, {"file_name": "158.bmp", "height": 128, "width": 128, "id": 504}, {"file_name": "098.bmp", "height": 128, "width": 128, "id": 505}, {"file_name": "1629.bmp", "height": 128, "width": 128, "id": 506}, {"file_name": "1856.bmp", "height": 128, "width": 128, "id": 507}, {"file_name": "915.bmp", "height": 128, "width": 128, "id": 508}, {"file_name": "255.bmp", "height": 128, "width": 128, "id": 510}, {"file_name": "1485.bmp", "height": 128, "width": 128, "id": 511}, {"file_name": "1359.bmp", "height": 128, "width": 128, "id": 512}, {"file_name": "499.bmp", "height": 128, "width": 128, "id": 513}, {"file_name": "411.bmp", "height": 128, "width": 128, "id": 514}, {"file_name": "772.bmp", "height": 128, "width": 128, "id": 515}, {"file_name": "1320.bmp", "height": 128, "width": 128, "id": 516}, {"file_name": "1194.bmp", "height": 128, "width": 128, "id": 517}, {"file_name": "434.bmp", "height": 128, "width": 128, "id": 518}, {"file_name": "503.bmp", "height": 128, "width": 128, "id": 519}, {"file_name": "1134.bmp", "height": 128, "width": 128, "id": 520}, {"file_name": "1521.bmp", "height": 128, "width": 128, "id": 521}, {"file_name": "988.bmp", "height": 128, "width": 128, "id": 522}, {"file_name": "073.bmp", "height": 128, "width": 128, "id": 523}, {"file_name": "366.bmp", "height": 128, "width": 128, "id": 526}, {"file_name": "1831.bmp", "height": 128, "width": 128, "id": 527}, {"file_name": "1437.bmp", "height": 128, "width": 128, "id": 528}, {"file_name": "412.bmp", "height": 128, "width": 128, "id": 529}, {"file_name": "190.bmp", "height": 128, "width": 128, "id": 530}, {"file_name": "1771.bmp", "height": 128, "width": 128, "id": 531}, {"file_name": "1500.bmp", "height": 128, "width": 128, "id": 533}, {"file_name": "809.bmp", "height": 128, "width": 128, "id": 534}, {"file_name": "303.bmp", "height": 128, "width": 128, "id": 535}, {"file_name": "1839.bmp", "height": 128, "width": 128, "id": 537}, {"file_name": "027.bmp", "height": 128, "width": 128, "id": 538}, {"file_name": "704.bmp", "height": 128, "width": 128, "id": 539}, {"file_name": "1820.bmp", "height": 128, "width": 128, "id": 540}, {"file_name": "795.bmp", "height": 128, "width": 128, "id": 541}, {"file_name": "1640.bmp", "height": 128, "width": 128, "id": 542}, {"file_name": "143.bmp", "height": 128, "width": 128, "id": 543}, {"file_name": "1779.bmp", "height": 128, "width": 128, "id": 544}, {"file_name": "690.bmp", "height": 128, "width": 128, "id": 546}, {"file_name": "421.bmp", "height": 128, "width": 128, "id": 547}, {"file_name": "518.bmp", "height": 128, "width": 128, "id": 549}, {"file_name": "1752.bmp", "height": 128, "width": 128, "id": 550}, {"file_name": "703.bmp", "height": 128, "width": 128, "id": 551}, {"file_name": "1520.bmp", "height": 128, "width": 128, "id": 552}, {"file_name": "1404.bmp", "height": 128, "width": 128, "id": 554}, {"file_name": "780.bmp", "height": 128, "width": 128, "id": 555}, {"file_name": "1277.bmp", "height": 128, "width": 128, "id": 556}, {"file_name": "1836.bmp", "height": 128, "width": 128, "id": 557}, {"file_name": "1329.bmp", "height": 128, "width": 128, "id": 558}, {"file_name": "1479.bmp", "height": 128, "width": 128, "id": 561}, {"file_name": "832.bmp", "height": 128, "width": 128, "id": 562}, {"file_name": "1476.bmp", "height": 128, "width": 128, "id": 563}, {"file_name": "037.bmp", "height": 128, "width": 128, "id": 564}, {"file_name": "1488.bmp", "height": 128, "width": 128, "id": 565}, {"file_name": "961.bmp", "height": 128, "width": 128, "id": 566}, {"file_name": "387.bmp", "height": 128, "width": 128, "id": 569}, {"file_name": "1319.bmp", "height": 128, "width": 128, "id": 570}, {"file_name": "1587.bmp", "height": 128, "width": 128, "id": 571}, {"file_name": "520.bmp", "height": 128, "width": 128, "id": 572}, {"file_name": "1220.bmp", "height": 128, "width": 128, "id": 574}, {"file_name": "1750.bmp", "height": 128, "width": 128, "id": 576}, {"file_name": "1896.bmp", "height": 128, "width": 128, "id": 577}, {"file_name": "1374.bmp", "height": 128, "width": 128, "id": 578}, {"file_name": "193.bmp", "height": 128, "width": 128, "id": 579}, {"file_name": "106.bmp", "height": 128, "width": 128, "id": 581}, {"file_name": "1317.bmp", "height": 128, "width": 128, "id": 582}, {"file_name": "1097.bmp", "height": 128, "width": 128, "id": 583}, {"file_name": "1234.bmp", "height": 128, "width": 128, "id": 584}, {"file_name": "1613.bmp", "height": 128, "width": 128, "id": 585}, {"file_name": "1252.bmp", "height": 128, "width": 128, "id": 586}, {"file_name": "1565.bmp", "height": 128, "width": 128, "id": 587}, {"file_name": "187.bmp", "height": 128, "width": 128, "id": 588}, {"file_name": "807.bmp", "height": 128, "width": 128, "id": 589}, {"file_name": "1226.bmp", "height": 128, "width": 128, "id": 590}, {"file_name": "160.bmp", "height": 128, "width": 128, "id": 591}, {"file_name": "1160.bmp", "height": 128, "width": 128, "id": 592}, {"file_name": "894.bmp", "height": 128, "width": 128, "id": 593}, {"file_name": "848.bmp", "height": 128, "width": 128, "id": 594}, {"file_name": "1684.bmp", "height": 128, "width": 128, "id": 595}, {"file_name": "930.bmp", "height": 128, "width": 128, "id": 596}, {"file_name": "1774.bmp", "height": 128, "width": 128, "id": 597}, {"file_name": "1315.bmp", "height": 128, "width": 128, "id": 598}, {"file_name": "712.bmp", "height": 128, "width": 128, "id": 599}, {"file_name": "971.bmp", "height": 128, "width": 128, "id": 600}, {"file_name": "1554.bmp", "height": 128, "width": 128, "id": 601}, {"file_name": "1128.bmp", "height": 128, "width": 128, "id": 602}, {"file_name": "129.bmp", "height": 128, "width": 128, "id": 603}, {"file_name": "1891.bmp", "height": 128, "width": 128, "id": 605}, {"file_name": "375.bmp", "height": 128, "width": 128, "id": 606}, {"file_name": "1901.bmp", "height": 128, "width": 128, "id": 607}, {"file_name": "1457.bmp", "height": 128, "width": 128, "id": 608}, {"file_name": "1417.bmp", "height": 128, "width": 128, "id": 611}, {"file_name": "591.bmp", "height": 128, "width": 128, "id": 612}, {"file_name": "790.bmp", "height": 128, "width": 128, "id": 613}, {"file_name": "1538.bmp", "height": 128, "width": 128, "id": 614}, {"file_name": "1527.bmp", "height": 128, "width": 128, "id": 615}, {"file_name": "662.bmp", "height": 128, "width": 128, "id": 616}, {"file_name": "095.bmp", "height": 128, "width": 128, "id": 617}, {"file_name": "824.bmp", "height": 128, "width": 128, "id": 618}, {"file_name": "692.bmp", "height": 128, "width": 128, "id": 619}, {"file_name": "252.bmp", "height": 128, "width": 128, "id": 620}, {"file_name": "1592.bmp", "height": 128, "width": 128, "id": 621}, {"file_name": "1650.bmp", "height": 128, "width": 128, "id": 622}, {"file_name": "126.bmp", "height": 128, "width": 128, "id": 623}, {"file_name": "1012.bmp", "height": 128, "width": 128, "id": 625}, {"file_name": "1100.bmp", "height": 128, "width": 128, "id": 627}, {"file_name": "455.bmp", "height": 128, "width": 128, "id": 628}, {"file_name": "840.bmp", "height": 128, "width": 128, "id": 629}, {"file_name": "329.bmp", "height": 128, "width": 128, "id": 630}, {"file_name": "1586.bmp", "height": 128, "width": 128, "id": 631}, {"file_name": "065.bmp", "height": 128, "width": 128, "id": 632}, {"file_name": "805.bmp", "height": 128, "width": 128, "id": 634}, {"file_name": "613.bmp", "height": 128, "width": 128, "id": 635}, {"file_name": "1829.bmp", "height": 128, "width": 128, "id": 636}, {"file_name": "984.bmp", "height": 128, "width": 128, "id": 637}, {"file_name": "537.bmp", "height": 128, "width": 128, "id": 638}, {"file_name": "569.bmp", "height": 128, "width": 128, "id": 639}, {"file_name": "1851.bmp", "height": 128, "width": 128, "id": 640}, {"file_name": "634.bmp", "height": 128, "width": 128, "id": 641}, {"file_name": "893.bmp", "height": 128, "width": 128, "id": 642}, {"file_name": "1325.bmp", "height": 128, "width": 128, "id": 643}, {"file_name": "1715.bmp", "height": 128, "width": 128, "id": 644}, {"file_name": "1739.bmp", "height": 128, "width": 128, "id": 645}, {"file_name": "1515.bmp", "height": 128, "width": 128, "id": 647}, {"file_name": "1766.bmp", "height": 128, "width": 128, "id": 648}, {"file_name": "593.bmp", "height": 128, "width": 128, "id": 649}, {"file_name": "1816.bmp", "height": 128, "width": 128, "id": 650}, {"file_name": "1607.bmp", "height": 128, "width": 128, "id": 651}, {"file_name": "291.bmp", "height": 128, "width": 128, "id": 652}, {"file_name": "1599.bmp", "height": 128, "width": 128, "id": 654}, {"file_name": "1336.bmp", "height": 128, "width": 128, "id": 657}, {"file_name": "1088.bmp", "height": 128, "width": 128, "id": 658}, {"file_name": "448.bmp", "height": 128, "width": 128, "id": 659}, {"file_name": "909.bmp", "height": 128, "width": 128, "id": 660}, {"file_name": "1885.bmp", "height": 128, "width": 128, "id": 661}, {"file_name": "1863.bmp", "height": 128, "width": 128, "id": 662}, {"file_name": "900.bmp", "height": 128, "width": 128, "id": 663}, {"file_name": "1524.bmp", "height": 128, "width": 128, "id": 664}, {"file_name": "028.bmp", "height": 128, "width": 128, "id": 665}, {"file_name": "1392.bmp", "height": 128, "width": 128, "id": 666}, {"file_name": "1838.bmp", "height": 128, "width": 128, "id": 667}, {"file_name": "289.bmp", "height": 128, "width": 128, "id": 668}, {"file_name": "009.bmp", "height": 128, "width": 128, "id": 669}, {"file_name": "756.bmp", "height": 128, "width": 128, "id": 670}, {"file_name": "064.bmp", "height": 128, "width": 128, "id": 671}, {"file_name": "1254.bmp", "height": 128, "width": 128, "id": 672}, {"file_name": "245.bmp", "height": 128, "width": 128, "id": 673}, {"file_name": "1173.bmp", "height": 128, "width": 128, "id": 675}, {"file_name": "1046.bmp", "height": 128, "width": 128, "id": 676}, {"file_name": "865.bmp", "height": 128, "width": 128, "id": 677}, {"file_name": "1873.bmp", "height": 128, "width": 128, "id": 678}, {"file_name": "684.bmp", "height": 128, "width": 128, "id": 679}, {"file_name": "1071.bmp", "height": 128, "width": 128, "id": 680}, {"file_name": "1736.bmp", "height": 128, "width": 128, "id": 682}, {"file_name": "295.bmp", "height": 128, "width": 128, "id": 683}, {"file_name": "1834.bmp", "height": 128, "width": 128, "id": 684}, {"file_name": "1504.bmp", "height": 128, "width": 128, "id": 685}, {"file_name": "420.bmp", "height": 128, "width": 128, "id": 686}, {"file_name": "1428.bmp", "height": 128, "width": 128, "id": 687}, {"file_name": "769.bmp", "height": 128, "width": 128, "id": 688}, {"file_name": "510.bmp", "height": 128, "width": 128, "id": 689}, {"file_name": "1704.bmp", "height": 128, "width": 128, "id": 690}, {"file_name": "268.bmp", "height": 128, "width": 128, "id": 691}, {"file_name": "395.bmp", "height": 128, "width": 128, "id": 693}, {"file_name": "1314.bmp", "height": 128, "width": 128, "id": 694}, {"file_name": "823.bmp", "height": 128, "width": 128, "id": 695}, {"file_name": "725.bmp", "height": 128, "width": 128, "id": 698}, {"file_name": "1883.bmp", "height": 128, "width": 128, "id": 699}, {"file_name": "1658.bmp", "height": 128, "width": 128, "id": 700}, {"file_name": "956.bmp", "height": 128, "width": 128, "id": 701}, {"file_name": "699.bmp", "height": 128, "width": 128, "id": 702}, {"file_name": "131.bmp", "height": 128, "width": 128, "id": 704}, {"file_name": "1583.bmp", "height": 128, "width": 128, "id": 705}, {"file_name": "118.bmp", "height": 128, "width": 128, "id": 706}, {"file_name": "1467.bmp", "height": 128, "width": 128, "id": 707}, {"file_name": "1386.bmp", "height": 128, "width": 128, "id": 708}, {"file_name": "759.bmp", "height": 128, "width": 128, "id": 709}, {"file_name": "825.bmp", "height": 128, "width": 128, "id": 710}, {"file_name": "1177.bmp", "height": 128, "width": 128, "id": 711}, {"file_name": "1439.bmp", "height": 128, "width": 128, "id": 714}, {"file_name": "1917.bmp", "height": 128, "width": 128, "id": 715}, {"file_name": "1680.bmp", "height": 128, "width": 128, "id": 716}, {"file_name": "1149.bmp", "height": 128, "width": 128, "id": 717}, {"file_name": "766.bmp", "height": 128, "width": 128, "id": 718}, {"file_name": "1634.bmp", "height": 128, "width": 128, "id": 720}, {"file_name": "1065.bmp", "height": 128, "width": 128, "id": 721}, {"file_name": "1585.bmp", "height": 128, "width": 128, "id": 722}, {"file_name": "866.bmp", "height": 128, "width": 128, "id": 723}, {"file_name": "1624.bmp", "height": 128, "width": 128, "id": 724}, {"file_name": "564.bmp", "height": 128, "width": 128, "id": 725}, {"file_name": "272.bmp", "height": 128, "width": 128, "id": 726}, {"file_name": "1323.bmp", "height": 128, "width": 128, "id": 727}, {"file_name": "133.bmp", "height": 128, "width": 128, "id": 728}, {"file_name": "1868.bmp", "height": 128, "width": 128, "id": 730}, {"file_name": "1278.bmp", "height": 128, "width": 128, "id": 731}, {"file_name": "022.bmp", "height": 128, "width": 128, "id": 733}, {"file_name": "1108.bmp", "height": 128, "width": 128, "id": 734}, {"file_name": "169.bmp", "height": 128, "width": 128, "id": 735}, {"file_name": "536.bmp", "height": 128, "width": 128, "id": 737}, {"file_name": "555.bmp", "height": 128, "width": 128, "id": 739}, {"file_name": "171.bmp", "height": 128, "width": 128, "id": 740}, {"file_name": "207.bmp", "height": 128, "width": 128, "id": 742}, {"file_name": "1727.bmp", "height": 128, "width": 128, "id": 743}, {"file_name": "253.bmp", "height": 128, "width": 128, "id": 744}, {"file_name": "1148.bmp", "height": 128, "width": 128, "id": 745}, {"file_name": "1098.bmp", "height": 128, "width": 128, "id": 746}, {"file_name": "1693.bmp", "height": 128, "width": 128, "id": 747}, {"file_name": "427.bmp", "height": 128, "width": 128, "id": 749}, {"file_name": "324.bmp", "height": 128, "width": 128, "id": 750}, {"file_name": "476.bmp", "height": 128, "width": 128, "id": 751}, {"file_name": "1283.bmp", "height": 128, "width": 128, "id": 752}, {"file_name": "1104.bmp", "height": 128, "width": 128, "id": 753}, {"file_name": "852.bmp", "height": 128, "width": 128, "id": 754}, {"file_name": "1260.bmp", "height": 128, "width": 128, "id": 755}, {"file_name": "1413.bmp", "height": 128, "width": 128, "id": 757}, {"file_name": "833.bmp", "height": 128, "width": 128, "id": 758}, {"file_name": "1828.bmp", "height": 128, "width": 128, "id": 759}, {"file_name": "1261.bmp", "height": 128, "width": 128, "id": 760}, {"file_name": "1464.bmp", "height": 128, "width": 128, "id": 762}, {"file_name": "1354.bmp", "height": 128, "width": 128, "id": 763}, {"file_name": "1625.bmp", "height": 128, "width": 128, "id": 764}, {"file_name": "1112.bmp", "height": 128, "width": 128, "id": 765}, {"file_name": "005.bmp", "height": 128, "width": 128, "id": 766}, {"file_name": "1578.bmp", "height": 128, "width": 128, "id": 767}, {"file_name": "1696.bmp", "height": 128, "width": 128, "id": 769}, {"file_name": "822.bmp", "height": 128, "width": 128, "id": 770}, {"file_name": "1615.bmp", "height": 128, "width": 128, "id": 773}, {"file_name": "384.bmp", "height": 128, "width": 128, "id": 774}, {"file_name": "696.bmp", "height": 128, "width": 128, "id": 775}, {"file_name": "1291.bmp", "height": 128, "width": 128, "id": 776}, {"file_name": "426.bmp", "height": 128, "width": 128, "id": 777}, {"file_name": "115.bmp", "height": 128, "width": 128, "id": 778}, {"file_name": "1276.bmp", "height": 128, "width": 128, "id": 779}, {"file_name": "1503.bmp", "height": 128, "width": 128, "id": 780}, {"file_name": "1676.bmp", "height": 128, "width": 128, "id": 781}, {"file_name": "804.bmp", "height": 128, "width": 128, "id": 782}, {"file_name": "1543.bmp", "height": 128, "width": 128, "id": 783}, {"file_name": "138.bmp", "height": 128, "width": 128, "id": 784}, {"file_name": "370.bmp", "height": 128, "width": 128, "id": 785}, {"file_name": "1880.bmp", "height": 128, "width": 128, "id": 787}, {"file_name": "1301.bmp", "height": 128, "width": 128, "id": 788}, {"file_name": "1400.bmp", "height": 128, "width": 128, "id": 789}, {"file_name": "341.bmp", "height": 128, "width": 128, "id": 791}, {"file_name": "1532.bmp", "height": 128, "width": 128, "id": 792}, {"file_name": "418.bmp", "height": 128, "width": 128, "id": 793}, {"file_name": "572.bmp", "height": 128, "width": 128, "id": 795}, {"file_name": "425.bmp", "height": 128, "width": 128, "id": 796}, {"file_name": "1860.bmp", "height": 128, "width": 128, "id": 797}, {"file_name": "105.bmp", "height": 128, "width": 128, "id": 800}, {"file_name": "718.bmp", "height": 128, "width": 128, "id": 801}, {"file_name": "1297.bmp", "height": 128, "width": 128, "id": 802}, {"file_name": "123.bmp", "height": 128, "width": 128, "id": 803}, {"file_name": "1163.bmp", "height": 128, "width": 128, "id": 805}, {"file_name": "661.bmp", "height": 128, "width": 128, "id": 806}, {"file_name": "1264.bmp", "height": 128, "width": 128, "id": 807}, {"file_name": "1632.bmp", "height": 128, "width": 128, "id": 809}, {"file_name": "844.bmp", "height": 128, "width": 128, "id": 810}, {"file_name": "006.bmp", "height": 128, "width": 128, "id": 811}, {"file_name": "543.bmp", "height": 128, "width": 128, "id": 812}, {"file_name": "679.bmp", "height": 128, "width": 128, "id": 813}, {"file_name": "1048.bmp", "height": 128, "width": 128, "id": 814}, {"file_name": "1781.bmp", "height": 128, "width": 128, "id": 815}, {"file_name": "213.bmp", "height": 128, "width": 128, "id": 816}, {"file_name": "345.bmp", "height": 128, "width": 128, "id": 818}, {"file_name": "753.bmp", "height": 128, "width": 128, "id": 819}, {"file_name": "1907.bmp", "height": 128, "width": 128, "id": 820}, {"file_name": "1408.bmp", "height": 128, "width": 128, "id": 821}, {"file_name": "059.bmp", "height": 128, "width": 128, "id": 822}, {"file_name": "868.bmp", "height": 128, "width": 128, "id": 823}, {"file_name": "566.bmp", "height": 128, "width": 128, "id": 824}, {"file_name": "474.bmp", "height": 128, "width": 128, "id": 825}, {"file_name": "966.bmp", "height": 128, "width": 128, "id": 826}, {"file_name": "363.bmp", "height": 128, "width": 128, "id": 827}, {"file_name": "953.bmp", "height": 128, "width": 128, "id": 828}, {"file_name": "338.bmp", "height": 128, "width": 128, "id": 829}, {"file_name": "1167.bmp", "height": 128, "width": 128, "id": 830}, {"file_name": "488.bmp", "height": 128, "width": 128, "id": 831}, {"file_name": "357.bmp", "height": 128, "width": 128, "id": 832}, {"file_name": "665.bmp", "height": 128, "width": 128, "id": 833}, {"file_name": "960.bmp", "height": 128, "width": 128, "id": 834}, {"file_name": "1646.bmp", "height": 128, "width": 128, "id": 836}, {"file_name": "969.bmp", "height": 128, "width": 128, "id": 837}, {"file_name": "054.bmp", "height": 128, "width": 128, "id": 838}, {"file_name": "1109.bmp", "height": 128, "width": 128, "id": 839}, {"file_name": "1198.bmp", "height": 128, "width": 128, "id": 840}, {"file_name": "586.bmp", "height": 128, "width": 128, "id": 841}, {"file_name": "1700.bmp", "height": 128, "width": 128, "id": 842}, {"file_name": "350.bmp", "height": 128, "width": 128, "id": 843}, {"file_name": "709.bmp", "height": 128, "width": 128, "id": 844}, {"file_name": "154.bmp", "height": 128, "width": 128, "id": 847}, {"file_name": "1837.bmp", "height": 128, "width": 128, "id": 848}, {"file_name": "1077.bmp", "height": 128, "width": 128, "id": 849}, {"file_name": "614.bmp", "height": 128, "width": 128, "id": 850}, {"file_name": "1219.bmp", "height": 128, "width": 128, "id": 852}, {"file_name": "035.bmp", "height": 128, "width": 128, "id": 853}, {"file_name": "330.bmp", "height": 128, "width": 128, "id": 854}, {"file_name": "643.bmp", "height": 128, "width": 128, "id": 855}, {"file_name": "724.bmp", "height": 128, "width": 128, "id": 856}, {"file_name": "764.bmp", "height": 128, "width": 128, "id": 857}, {"file_name": "672.bmp", "height": 128, "width": 128, "id": 858}, {"file_name": "1546.bmp", "height": 128, "width": 128, "id": 859}, {"file_name": "1008.bmp", "height": 128, "width": 128, "id": 860}, {"file_name": "1152.bmp", "height": 128, "width": 128, "id": 861}, {"file_name": "1396.bmp", "height": 128, "width": 128, "id": 862}, {"file_name": "767.bmp", "height": 128, "width": 128, "id": 863}, {"file_name": "1872.bmp", "height": 128, "width": 128, "id": 864}, {"file_name": "121.bmp", "height": 128, "width": 128, "id": 865}, {"file_name": "1381.bmp", "height": 128, "width": 128, "id": 867}, {"file_name": "048.bmp", "height": 128, "width": 128, "id": 868}, {"file_name": "1116.bmp", "height": 128, "width": 128, "id": 869}, {"file_name": "1481.bmp", "height": 128, "width": 128, "id": 870}, {"file_name": "454.bmp", "height": 128, "width": 128, "id": 871}, {"file_name": "1663.bmp", "height": 128, "width": 128, "id": 872}, {"file_name": "128.bmp", "height": 128, "width": 128, "id": 873}, {"file_name": "067.bmp", "height": 128, "width": 128, "id": 874}, {"file_name": "936.bmp", "height": 128, "width": 128, "id": 875}, {"file_name": "1049.bmp", "height": 128, "width": 128, "id": 876}, {"file_name": "1769.bmp", "height": 128, "width": 128, "id": 877}, {"file_name": "391.bmp", "height": 128, "width": 128, "id": 878}, {"file_name": "1510.bmp", "height": 128, "width": 128, "id": 880}, {"file_name": "1262.bmp", "height": 128, "width": 128, "id": 881}, {"file_name": "197.bmp", "height": 128, "width": 128, "id": 882}, {"file_name": "919.bmp", "height": 128, "width": 128, "id": 883}, {"file_name": "1135.bmp", "height": 128, "width": 128, "id": 884}, {"file_name": "1139.bmp", "height": 128, "width": 128, "id": 885}, {"file_name": "103.bmp", "height": 128, "width": 128, "id": 886}, {"file_name": "1900.bmp", "height": 128, "width": 128, "id": 887}, {"file_name": "835.bmp", "height": 128, "width": 128, "id": 888}, {"file_name": "1339.bmp", "height": 128, "width": 128, "id": 889}, {"file_name": "751.bmp", "height": 128, "width": 128, "id": 890}, {"file_name": "114.bmp", "height": 128, "width": 128, "id": 891}, {"file_name": "1081.bmp", "height": 128, "width": 128, "id": 892}, {"file_name": "693.bmp", "height": 128, "width": 128, "id": 893}, {"file_name": "1357.bmp", "height": 128, "width": 128, "id": 894}, {"file_name": "1513.bmp", "height": 128, "width": 128, "id": 895}, {"file_name": "1302.bmp", "height": 128, "width": 128, "id": 896}, {"file_name": "1800.bmp", "height": 128, "width": 128, "id": 897}, {"file_name": "1360.bmp", "height": 128, "width": 128, "id": 899}, {"file_name": "1848.bmp", "height": 128, "width": 128, "id": 900}, {"file_name": "1570.bmp", "height": 128, "width": 128, "id": 901}, {"file_name": "1796.bmp", "height": 128, "width": 128, "id": 902}, {"file_name": "1842.bmp", "height": 128, "width": 128, "id": 904}, {"file_name": "202.bmp", "height": 128, "width": 128, "id": 905}, {"file_name": "484.bmp", "height": 128, "width": 128, "id": 906}, {"file_name": "1265.bmp", "height": 128, "width": 128, "id": 907}, {"file_name": "1890.bmp", "height": 128, "width": 128, "id": 908}, {"file_name": "1636.bmp", "height": 128, "width": 128, "id": 910}, {"file_name": "176.bmp", "height": 128, "width": 128, "id": 911}, {"file_name": "628.bmp", "height": 128, "width": 128, "id": 912}, {"file_name": "1348.bmp", "height": 128, "width": 128, "id": 913}, {"file_name": "400.bmp", "height": 128, "width": 128, "id": 914}, {"file_name": "1512.bmp", "height": 128, "width": 128, "id": 915}, {"file_name": "072.bmp", "height": 128, "width": 128, "id": 916}, {"file_name": "304.bmp", "height": 128, "width": 128, "id": 917}, {"file_name": "018.bmp", "height": 128, "width": 128, "id": 918}, {"file_name": "1463.bmp", "height": 128, "width": 128, "id": 919}, {"file_name": "931.bmp", "height": 128, "width": 128, "id": 920}, {"file_name": "273.bmp", "height": 128, "width": 128, "id": 921}, {"file_name": "1244.bmp", "height": 128, "width": 128, "id": 922}, {"file_name": "1078.bmp", "height": 128, "width": 128, "id": 924}, {"file_name": "1603.bmp", "height": 128, "width": 128, "id": 925}, {"file_name": "1241.bmp", "height": 128, "width": 128, "id": 926}, {"file_name": "020.bmp", "height": 128, "width": 128, "id": 927}, {"file_name": "1489.bmp", "height": 128, "width": 128, "id": 928}, {"file_name": "1287.bmp", "height": 128, "width": 128, "id": 929}, {"file_name": "031.bmp", "height": 128, "width": 128, "id": 931}, {"file_name": "680.bmp", "height": 128, "width": 128, "id": 932}, {"file_name": "1023.bmp", "height": 128, "width": 128, "id": 933}, {"file_name": "1119.bmp", "height": 128, "width": 128, "id": 934}, {"file_name": "1882.bmp", "height": 128, "width": 128, "id": 935}, {"file_name": "682.bmp", "height": 128, "width": 128, "id": 936}, {"file_name": "319.bmp", "height": 128, "width": 128, "id": 937}, {"file_name": "063.bmp", "height": 128, "width": 128, "id": 938}, {"file_name": "1430.bmp", "height": 128, "width": 128, "id": 939}, {"file_name": "1174.bmp", "height": 128, "width": 128, "id": 940}, {"file_name": "1605.bmp", "height": 128, "width": 128, "id": 941}, {"file_name": "002.bmp", "height": 128, "width": 128, "id": 942}, {"file_name": "964.bmp", "height": 128, "width": 128, "id": 943}, {"file_name": "1735.bmp", "height": 128, "width": 128, "id": 944}, {"file_name": "787.bmp", "height": 128, "width": 128, "id": 945}, {"file_name": "1155.bmp", "height": 128, "width": 128, "id": 946}, {"file_name": "939.bmp", "height": 128, "width": 128, "id": 947}, {"file_name": "1322.bmp", "height": 128, "width": 128, "id": 948}, {"file_name": "1560.bmp", "height": 128, "width": 128, "id": 949}, {"file_name": "1052.bmp", "height": 128, "width": 128, "id": 950}, {"file_name": "972.bmp", "height": 128, "width": 128, "id": 952}, {"file_name": "539.bmp", "height": 128, "width": 128, "id": 953}, {"file_name": "225.bmp", "height": 128, "width": 128, "id": 954}, {"file_name": "1337.bmp", "height": 128, "width": 128, "id": 955}, {"file_name": "668.bmp", "height": 128, "width": 128, "id": 957}, {"file_name": "342.bmp", "height": 128, "width": 128, "id": 958}, {"file_name": "278.bmp", "height": 128, "width": 128, "id": 959}, {"file_name": "853.bmp", "height": 128, "width": 128, "id": 960}, {"file_name": "1205.bmp", "height": 128, "width": 128, "id": 961}, {"file_name": "815.bmp", "height": 128, "width": 128, "id": 962}, {"file_name": "607.bmp", "height": 128, "width": 128, "id": 963}, {"file_name": "935.bmp", "height": 128, "width": 128, "id": 964}, {"file_name": "1266.bmp", "height": 128, "width": 128, "id": 965}, {"file_name": "1029.bmp", "height": 128, "width": 128, "id": 966}, {"file_name": "1269.bmp", "height": 128, "width": 128, "id": 967}, {"file_name": "1344.bmp", "height": 128, "width": 128, "id": 968}, {"file_name": "328.bmp", "height": 128, "width": 128, "id": 970}, {"file_name": "1920.bmp", "height": 128, "width": 128, "id": 971}, {"file_name": "1536.bmp", "height": 128, "width": 128, "id": 973}, {"file_name": "1307.bmp", "height": 128, "width": 128, "id": 975}, {"file_name": "743.bmp", "height": 128, "width": 128, "id": 976}, {"file_name": "220.bmp", "height": 128, "width": 128, "id": 977}, {"file_name": "658.bmp", "height": 128, "width": 128, "id": 978}, {"file_name": "1050.bmp", "height": 128, "width": 128, "id": 980}, {"file_name": "746.bmp", "height": 128, "width": 128, "id": 981}, {"file_name": "912.bmp", "height": 128, "width": 128, "id": 982}, {"file_name": "1649.bmp", "height": 128, "width": 128, "id": 985}, {"file_name": "1497.bmp", "height": 128, "width": 128, "id": 986}, {"file_name": "1641.bmp", "height": 128, "width": 128, "id": 987}, {"file_name": "676.bmp", "height": 128, "width": 128, "id": 989}, {"file_name": "087.bmp", "height": 128, "width": 128, "id": 990}, {"file_name": "688.bmp", "height": 128, "width": 128, "id": 991}, {"file_name": "1164.bmp", "height": 128, "width": 128, "id": 992}, {"file_name": "1550.bmp", "height": 128, "width": 128, "id": 993}, {"file_name": "514.bmp", "height": 128, "width": 128, "id": 995}, {"file_name": "1511.bmp", "height": 128, "width": 128, "id": 997}, {"file_name": "1746.bmp", "height": 128, "width": 128, "id": 998}, {"file_name": "306.bmp", "height": 128, "width": 128, "id": 999}, {"file_name": "788.bmp", "height": 128, "width": 128, "id": 1000}, {"file_name": "441.bmp", "height": 128, "width": 128, "id": 1003}, {"file_name": "907.bmp", "height": 128, "width": 128, "id": 1004}, {"file_name": "1733.bmp", "height": 128, "width": 128, "id": 1005}, {"file_name": "1574.bmp", "height": 128, "width": 128, "id": 1006}, {"file_name": "622.bmp", "height": 128, "width": 128, "id": 1007}, {"file_name": "1656.bmp", "height": 128, "width": 128, "id": 1008}, {"file_name": "1754.bmp", "height": 128, "width": 128, "id": 1009}, {"file_name": "563.bmp", "height": 128, "width": 128, "id": 1010}, {"file_name": "839.bmp", "height": 128, "width": 128, "id": 1011}, {"file_name": "344.bmp", "height": 128, "width": 128, "id": 1012}, {"file_name": "917.bmp", "height": 128, "width": 128, "id": 1013}, {"file_name": "013.bmp", "height": 128, "width": 128, "id": 1014}, {"file_name": "576.bmp", "height": 128, "width": 128, "id": 1015}, {"file_name": "549.bmp", "height": 128, "width": 128, "id": 1016}, {"file_name": "1143.bmp", "height": 128, "width": 128, "id": 1017}, {"file_name": "500.bmp", "height": 128, "width": 128, "id": 1018}, {"file_name": "260.bmp", "height": 128, "width": 128, "id": 1019}, {"file_name": "249.bmp", "height": 128, "width": 128, "id": 1020}, {"file_name": "1461.bmp", "height": 128, "width": 128, "id": 1021}, {"file_name": "1070.bmp", "height": 128, "width": 128, "id": 1023}, {"file_name": "1678.bmp", "height": 128, "width": 128, "id": 1024}, {"file_name": "1496.bmp", "height": 128, "width": 128, "id": 1025}, {"file_name": "1086.bmp", "height": 128, "width": 128, "id": 1026}, {"file_name": "1720.bmp", "height": 128, "width": 128, "id": 1027}, {"file_name": "1529.bmp", "height": 128, "width": 128, "id": 1029}, {"file_name": "1420.bmp", "height": 128, "width": 128, "id": 1030}, {"file_name": "409.bmp", "height": 128, "width": 128, "id": 1032}, {"file_name": "1406.bmp", "height": 128, "width": 128, "id": 1033}, {"file_name": "1402.bmp", "height": 128, "width": 128, "id": 1034}, {"file_name": "934.bmp", "height": 128, "width": 128, "id": 1035}, {"file_name": "372.bmp", "height": 128, "width": 128, "id": 1037}, {"file_name": "360.bmp", "height": 128, "width": 128, "id": 1038}, {"file_name": "792.bmp", "height": 128, "width": 128, "id": 1039}, {"file_name": "1010.bmp", "height": 128, "width": 128, "id": 1041}, {"file_name": "567.bmp", "height": 128, "width": 128, "id": 1042}, {"file_name": "286.bmp", "height": 128, "width": 128, "id": 1043}, {"file_name": "288.bmp", "height": 128, "width": 128, "id": 1044}, {"file_name": "1673.bmp", "height": 128, "width": 128, "id": 1045}, {"file_name": "945.bmp", "height": 128, "width": 128, "id": 1046}, {"file_name": "955.bmp", "height": 128, "width": 128, "id": 1048}, {"file_name": "1576.bmp", "height": 128, "width": 128, "id": 1049}, {"file_name": "616.bmp", "height": 128, "width": 128, "id": 1050}, {"file_name": "949.bmp", "height": 128, "width": 128, "id": 1051}, {"file_name": "1571.bmp", "height": 128, "width": 128, "id": 1053}, {"file_name": "1726.bmp", "height": 128, "width": 128, "id": 1054}, {"file_name": "1295.bmp", "height": 128, "width": 128, "id": 1055}, {"file_name": "1036.bmp", "height": 128, "width": 128, "id": 1056}, {"file_name": "991.bmp", "height": 128, "width": 128, "id": 1058}, {"file_name": "511.bmp", "height": 128, "width": 128, "id": 1059}, {"file_name": "810.bmp", "height": 128, "width": 128, "id": 1060}, {"file_name": "175.bmp", "height": 128, "width": 128, "id": 1061}, {"file_name": "1009.bmp", "height": 128, "width": 128, "id": 1062}, {"file_name": "1235.bmp", "height": 128, "width": 128, "id": 1063}, {"file_name": "711.bmp", "height": 128, "width": 128, "id": 1064}, {"file_name": "466.bmp", "height": 128, "width": 128, "id": 1066}, {"file_name": "505.bmp", "height": 128, "width": 128, "id": 1067}, {"file_name": "522.bmp", "height": 128, "width": 128, "id": 1068}, {"file_name": "239.bmp", "height": 128, "width": 128, "id": 1069}, {"file_name": "405.bmp", "height": 128, "width": 128, "id": 1070}, {"file_name": "948.bmp", "height": 128, "width": 128, "id": 1072}, {"file_name": "1548.bmp", "height": 128, "width": 128, "id": 1073}, {"file_name": "1189.bmp", "height": 128, "width": 128, "id": 1074}, {"file_name": "406.bmp", "height": 128, "width": 128, "id": 1075}, {"file_name": "1286.bmp", "height": 128, "width": 128, "id": 1076}, {"file_name": "1069.bmp", "height": 128, "width": 128, "id": 1077}, {"file_name": "258.bmp", "height": 128, "width": 128, "id": 1078}, {"file_name": "159.bmp", "height": 128, "width": 128, "id": 1079}, {"file_name": "1369.bmp", "height": 128, "width": 128, "id": 1080}, {"file_name": "1162.bmp", "height": 128, "width": 128, "id": 1081}, {"file_name": "1498.bmp", "height": 128, "width": 128, "id": 1082}, {"file_name": "1056.bmp", "height": 128, "width": 128, "id": 1083}, {"file_name": "1556.bmp", "height": 128, "width": 128, "id": 1084}, {"file_name": "177.bmp", "height": 128, "width": 128, "id": 1086}, {"file_name": "659.bmp", "height": 128, "width": 128, "id": 1087}, {"file_name": "1142.bmp", "height": 128, "width": 128, "id": 1088}, {"file_name": "238.bmp", "height": 128, "width": 128, "id": 1089}, {"file_name": "928.bmp", "height": 128, "width": 128, "id": 1090}, {"file_name": "1617.bmp", "height": 128, "width": 128, "id": 1091}, {"file_name": "110.bmp", "height": 128, "width": 128, "id": 1092}, {"file_name": "386.bmp", "height": 128, "width": 128, "id": 1094}, {"file_name": "798.bmp", "height": 128, "width": 128, "id": 1095}, {"file_name": "382.bmp", "height": 128, "width": 128, "id": 1096}, {"file_name": "1115.bmp", "height": 128, "width": 128, "id": 1098}, {"file_name": "1211.bmp", "height": 128, "width": 128, "id": 1099}, {"file_name": "1905.bmp", "height": 128, "width": 128, "id": 1101}, {"file_name": "1850.bmp", "height": 128, "width": 128, "id": 1104}, {"file_name": "732.bmp", "height": 128, "width": 128, "id": 1107}, {"file_name": "079.bmp", "height": 128, "width": 128, "id": 1108}, {"file_name": "519.bmp", "height": 128, "width": 128, "id": 1109}, {"file_name": "799.bmp", "height": 128, "width": 128, "id": 1110}, {"file_name": "1236.bmp", "height": 128, "width": 128, "id": 1111}, {"file_name": "1193.bmp", "height": 128, "width": 128, "id": 1112}, {"file_name": "088.bmp", "height": 128, "width": 128, "id": 1113}, {"file_name": "925.bmp", "height": 128, "width": 128, "id": 1114}, {"file_name": "1154.bmp", "height": 128, "width": 128, "id": 1115}, {"file_name": "1131.bmp", "height": 128, "width": 128, "id": 1116}, {"file_name": "292.bmp", "height": 128, "width": 128, "id": 1118}, {"file_name": "043.bmp", "height": 128, "width": 128, "id": 1119}, {"file_name": "1557.bmp", "height": 128, "width": 128, "id": 1120}, {"file_name": "559.bmp", "height": 128, "width": 128, "id": 1121}, {"file_name": "889.bmp", "height": 128, "width": 128, "id": 1123}, {"file_name": "550.bmp", "height": 128, "width": 128, "id": 1125}, {"file_name": "513.bmp", "height": 128, "width": 128, "id": 1126}, {"file_name": "349.bmp", "height": 128, "width": 128, "id": 1127}, {"file_name": "1064.bmp", "height": 128, "width": 128, "id": 1128}, {"file_name": "1870.bmp", "height": 128, "width": 128, "id": 1129}, {"file_name": "1184.bmp", "height": 128, "width": 128, "id": 1132}, {"file_name": "1487.bmp", "height": 128, "width": 128, "id": 1135}, {"file_name": "1783.bmp", "height": 128, "width": 128, "id": 1136}, {"file_name": "1114.bmp", "height": 128, "width": 128, "id": 1137}, {"file_name": "994.bmp", "height": 128, "width": 128, "id": 1139}, {"file_name": "1878.bmp", "height": 128, "width": 128, "id": 1140}, {"file_name": "1053.bmp", "height": 128, "width": 128, "id": 1142}, {"file_name": "1156.bmp", "height": 128, "width": 128, "id": 1143}, {"file_name": "1817.bmp", "height": 128, "width": 128, "id": 1144}, {"file_name": "1709.bmp", "height": 128, "width": 128, "id": 1145}, {"file_name": "204.bmp", "height": 128, "width": 128, "id": 1146}, {"file_name": "1914.bmp", "height": 128, "width": 128, "id": 1147}, {"file_name": "1022.bmp", "height": 128, "width": 128, "id": 1148}, {"file_name": "1590.bmp", "height": 128, "width": 128, "id": 1149}, {"file_name": "752.bmp", "height": 128, "width": 128, "id": 1150}, {"file_name": "1659.bmp", "height": 128, "width": 128, "id": 1151}, {"file_name": "1271.bmp", "height": 128, "width": 128, "id": 1152}, {"file_name": "008.bmp", "height": 128, "width": 128, "id": 1153}, {"file_name": "025.bmp", "height": 128, "width": 128, "id": 1154}, {"file_name": "077.bmp", "height": 128, "width": 128, "id": 1156}, {"file_name": "122.bmp", "height": 128, "width": 128, "id": 1157}, {"file_name": "452.bmp", "height": 128, "width": 128, "id": 1160}, {"file_name": "151.bmp", "height": 128, "width": 128, "id": 1161}, {"file_name": "1259.bmp", "height": 128, "width": 128, "id": 1162}, {"file_name": "135.bmp", "height": 128, "width": 128, "id": 1163}, {"file_name": "1206.bmp", "height": 128, "width": 128, "id": 1164}, {"file_name": "1847.bmp", "height": 128, "width": 128, "id": 1166}, {"file_name": "525.bmp", "height": 128, "width": 128, "id": 1167}, {"file_name": "1691.bmp", "height": 128, "width": 128, "id": 1168}, {"file_name": "1852.bmp", "height": 128, "width": 128, "id": 1169}, {"file_name": "1057.bmp", "height": 128, "width": 128, "id": 1170}, {"file_name": "1466.bmp", "height": 128, "width": 128, "id": 1171}, {"file_name": "142.bmp", "height": 128, "width": 128, "id": 1173}, {"file_name": "058.bmp", "height": 128, "width": 128, "id": 1174}, {"file_name": "1441.bmp", "height": 128, "width": 128, "id": 1175}, {"file_name": "459.bmp", "height": 128, "width": 128, "id": 1176}, {"file_name": "243.bmp", "height": 128, "width": 128, "id": 1177}, {"file_name": "465.bmp", "height": 128, "width": 128, "id": 1178}, {"file_name": "650.bmp", "height": 128, "width": 128, "id": 1179}, {"file_name": "050.bmp", "height": 128, "width": 128, "id": 1180}, {"file_name": "1768.bmp", "height": 128, "width": 128, "id": 1181}, {"file_name": "165.bmp", "height": 128, "width": 128, "id": 1182}, {"file_name": "1553.bmp", "height": 128, "width": 128, "id": 1183}, {"file_name": "589.bmp", "height": 128, "width": 128, "id": 1184}, {"file_name": "361.bmp", "height": 128, "width": 128, "id": 1185}, {"file_name": "1480.bmp", "height": 128, "width": 128, "id": 1186}, {"file_name": "247.bmp", "height": 128, "width": 128, "id": 1187}, {"file_name": "1310.bmp", "height": 128, "width": 128, "id": 1188}, {"file_name": "015.bmp", "height": 128, "width": 128, "id": 1190}, {"file_name": "1435.bmp", "height": 128, "width": 128, "id": 1191}, {"file_name": "1378.bmp", "height": 128, "width": 128, "id": 1192}, {"file_name": "1082.bmp", "height": 128, "width": 128, "id": 1193}, {"file_name": "364.bmp", "height": 128, "width": 128, "id": 1194}, {"file_name": "819.bmp", "height": 128, "width": 128, "id": 1195}, {"file_name": "1462.bmp", "height": 128, "width": 128, "id": 1196}, {"file_name": "1743.bmp", "height": 128, "width": 128, "id": 1197}, {"file_name": "401.bmp", "height": 128, "width": 128, "id": 1198}, {"file_name": "413.bmp", "height": 128, "width": 128, "id": 1199}, {"file_name": "237.bmp", "height": 128, "width": 128, "id": 1200}, {"file_name": "1197.bmp", "height": 128, "width": 128, "id": 1201}, {"file_name": "332.bmp", "height": 128, "width": 128, "id": 1202}, {"file_name": "538.bmp", "height": 128, "width": 128, "id": 1203}, {"file_name": "1058.bmp", "height": 128, "width": 128, "id": 1204}, {"file_name": "1004.bmp", "height": 128, "width": 128, "id": 1205}, {"file_name": "1316.bmp", "height": 128, "width": 128, "id": 1208}, {"file_name": "1106.bmp", "height": 128, "width": 128, "id": 1209}, {"file_name": "647.bmp", "height": 128, "width": 128, "id": 1210}, {"file_name": "618.bmp", "height": 128, "width": 128, "id": 1211}, {"file_name": "1352.bmp", "height": 128, "width": 128, "id": 1212}, {"file_name": "641.bmp", "height": 128, "width": 128, "id": 1213}, {"file_name": "1275.bmp", "height": 128, "width": 128, "id": 1214}, {"file_name": "1171.bmp", "height": 128, "width": 128, "id": 1215}, {"file_name": "150.bmp", "height": 128, "width": 128, "id": 1216}, {"file_name": "553.bmp", "height": 128, "width": 128, "id": 1218}, {"file_name": "773.bmp", "height": 128, "width": 128, "id": 1219}, {"file_name": "861.bmp", "height": 128, "width": 128, "id": 1220}, {"file_name": "947.bmp", "height": 128, "width": 128, "id": 1221}, {"file_name": "1869.bmp", "height": 128, "width": 128, "id": 1222}, {"file_name": "734.bmp", "height": 128, "width": 128, "id": 1225}, {"file_name": "1669.bmp", "height": 128, "width": 128, "id": 1226}, {"file_name": "1738.bmp", "height": 128, "width": 128, "id": 1227}, {"file_name": "449.bmp", "height": 128, "width": 128, "id": 1228}, {"file_name": "1137.bmp", "height": 128, "width": 128, "id": 1229}, {"file_name": "1124.bmp", "height": 128, "width": 128, "id": 1231}, {"file_name": "729.bmp", "height": 128, "width": 128, "id": 1232}, {"file_name": "1068.bmp", "height": 128, "width": 128, "id": 1233}, {"file_name": "762.bmp", "height": 128, "width": 128, "id": 1234}, {"file_name": "1367.bmp", "height": 128, "width": 128, "id": 1235}, {"file_name": "827.bmp", "height": 128, "width": 128, "id": 1236}, {"file_name": "1411.bmp", "height": 128, "width": 128, "id": 1237}, {"file_name": "423.bmp", "height": 128, "width": 128, "id": 1238}, {"file_name": "965.bmp", "height": 128, "width": 128, "id": 1239}, {"file_name": "1672.bmp", "height": 128, "width": 128, "id": 1240}, {"file_name": "938.bmp", "height": 128, "width": 128, "id": 1241}, {"file_name": "1682.bmp", "height": 128, "width": 128, "id": 1242}, {"file_name": "236.bmp", "height": 128, "width": 128, "id": 1243}, {"file_name": "702.bmp", "height": 128, "width": 128, "id": 1244}, {"file_name": "1855.bmp", "height": 128, "width": 128, "id": 1245}, {"file_name": "1899.bmp", "height": 128, "width": 128, "id": 1246}, {"file_name": "918.bmp", "height": 128, "width": 128, "id": 1247}, {"file_name": "1172.bmp", "height": 128, "width": 128, "id": 1248}, {"file_name": "967.bmp", "height": 128, "width": 128, "id": 1249}, {"file_name": "671.bmp", "height": 128, "width": 128, "id": 1250}, {"file_name": "775.bmp", "height": 128, "width": 128, "id": 1251}, {"file_name": "1176.bmp", "height": 128, "width": 128, "id": 1252}, {"file_name": "978.bmp", "height": 128, "width": 128, "id": 1253}, {"file_name": "1875.bmp", "height": 128, "width": 128, "id": 1254}, {"file_name": "1908.bmp", "height": 128, "width": 128, "id": 1255}, {"file_name": "1245.bmp", "height": 128, "width": 128, "id": 1256}, {"file_name": "558.bmp", "height": 128, "width": 128, "id": 1257}, {"file_name": "1227.bmp", "height": 128, "width": 128, "id": 1258}, {"file_name": "1019.bmp", "height": 128, "width": 128, "id": 1259}, {"file_name": "1425.bmp", "height": 128, "width": 128, "id": 1260}, {"file_name": "184.bmp", "height": 128, "width": 128, "id": 1261}, {"file_name": "548.bmp", "height": 128, "width": 128, "id": 1262}, {"file_name": "1630.bmp", "height": 128, "width": 128, "id": 1263}, {"file_name": "1758.bmp", "height": 128, "width": 128, "id": 1264}, {"file_name": "1343.bmp", "height": 128, "width": 128, "id": 1265}, {"file_name": "1674.bmp", "height": 128, "width": 128, "id": 1266}, {"file_name": "1456.bmp", "height": 128, "width": 128, "id": 1267}, {"file_name": "351.bmp", "height": 128, "width": 128, "id": 1268}, {"file_name": "533.bmp", "height": 128, "width": 128, "id": 1269}, {"file_name": "1572.bmp", "height": 128, "width": 128, "id": 1271}, {"file_name": "1255.bmp", "height": 128, "width": 128, "id": 1272}, {"file_name": "1338.bmp", "height": 128, "width": 128, "id": 1273}, {"file_name": "1797.bmp", "height": 128, "width": 128, "id": 1274}, {"file_name": "989.bmp", "height": 128, "width": 128, "id": 1277}, {"file_name": "1652.bmp", "height": 128, "width": 128, "id": 1279}, {"file_name": "1436.bmp", "height": 128, "width": 128, "id": 1280}, {"file_name": "770.bmp", "height": 128, "width": 128, "id": 1281}, {"file_name": "1465.bmp", "height": 128, "width": 128, "id": 1282}, {"file_name": "436.bmp", "height": 128, "width": 128, "id": 1283}, {"file_name": "1522.bmp", "height": 128, "width": 128, "id": 1286}, {"file_name": "166.bmp", "height": 128, "width": 128, "id": 1287}, {"file_name": "1001.bmp", "height": 128, "width": 128, "id": 1289}, {"file_name": "1755.bmp", "height": 128, "width": 128, "id": 1290}, {"file_name": "617.bmp", "height": 128, "width": 128, "id": 1291}, {"file_name": "594.bmp", "height": 128, "width": 128, "id": 1292}, {"file_name": "422.bmp", "height": 128, "width": 128, "id": 1294}, {"file_name": "571.bmp", "height": 128, "width": 128, "id": 1295}, {"file_name": "1519.bmp", "height": 128, "width": 128, "id": 1296}, {"file_name": "828.bmp", "height": 128, "width": 128, "id": 1299}, {"file_name": "1757.bmp", "height": 128, "width": 128, "id": 1301}, {"file_name": "508.bmp", "height": 128, "width": 128, "id": 1302}, {"file_name": "1257.bmp", "height": 128, "width": 128, "id": 1305}, {"file_name": "903.bmp", "height": 128, "width": 128, "id": 1307}, {"file_name": "983.bmp", "height": 128, "width": 128, "id": 1308}, {"file_name": "1042.bmp", "height": 128, "width": 128, "id": 1309}, {"file_name": "1247.bmp", "height": 128, "width": 128, "id": 1310}, {"file_name": "404.bmp", "height": 128, "width": 128, "id": 1311}, {"file_name": "491.bmp", "height": 128, "width": 128, "id": 1312}, {"file_name": "1671.bmp", "height": 128, "width": 128, "id": 1313}, {"file_name": "1728.bmp", "height": 128, "width": 128, "id": 1314}, {"file_name": "744.bmp", "height": 128, "width": 128, "id": 1315}, {"file_name": "1447.bmp", "height": 128, "width": 128, "id": 1316}, {"file_name": "240.bmp", "height": 128, "width": 128, "id": 1317}, {"file_name": "621.bmp", "height": 128, "width": 128, "id": 1318}, {"file_name": "1272.bmp", "height": 128, "width": 128, "id": 1319}, {"file_name": "624.bmp", "height": 128, "width": 128, "id": 1320}, {"file_name": "1448.bmp", "height": 128, "width": 128, "id": 1321}, {"file_name": "630.bmp", "height": 128, "width": 128, "id": 1322}, {"file_name": "1651.bmp", "height": 128, "width": 128, "id": 1323}, {"file_name": "437.bmp", "height": 128, "width": 128, "id": 1324}, {"file_name": "1484.bmp", "height": 128, "width": 128, "id": 1325}, {"file_name": "1410.bmp", "height": 128, "width": 128, "id": 1326}, {"file_name": "493.bmp", "height": 128, "width": 128, "id": 1330}, {"file_name": "250.bmp", "height": 128, "width": 128, "id": 1331}, {"file_name": "898.bmp", "height": 128, "width": 128, "id": 1333}, {"file_name": "913.bmp", "height": 128, "width": 128, "id": 1336}, {"file_name": "1547.bmp", "height": 128, "width": 128, "id": 1337}, {"file_name": "1099.bmp", "height": 128, "width": 128, "id": 1338}, {"file_name": "1006.bmp", "height": 128, "width": 128, "id": 1339}, {"file_name": "1858.bmp", "height": 128, "width": 128, "id": 1340}, {"file_name": "296.bmp", "height": 128, "width": 128, "id": 1341}, {"file_name": "1215.bmp", "height": 128, "width": 128, "id": 1342}, {"file_name": "440.bmp", "height": 128, "width": 128, "id": 1343}, {"file_name": "284.bmp", "height": 128, "width": 128, "id": 1344}, {"file_name": "1508.bmp", "height": 128, "width": 128, "id": 1345}, {"file_name": "645.bmp", "height": 128, "width": 128, "id": 1347}, {"file_name": "1243.bmp", "height": 128, "width": 128, "id": 1348}, {"file_name": "180.bmp", "height": 128, "width": 128, "id": 1350}, {"file_name": "221.bmp", "height": 128, "width": 128, "id": 1351}, {"file_name": "262.bmp", "height": 128, "width": 128, "id": 1352}, {"file_name": "1380.bmp", "height": 128, "width": 128, "id": 1353}, {"file_name": "1446.bmp", "height": 128, "width": 128, "id": 1354}, {"file_name": "1544.bmp", "height": 128, "width": 128, "id": 1355}, {"file_name": "1523.bmp", "height": 128, "width": 128, "id": 1356}, {"file_name": "897.bmp", "height": 128, "width": 128, "id": 1357}, {"file_name": "530.bmp", "height": 128, "width": 128, "id": 1358}, {"file_name": "639.bmp", "height": 128, "width": 128, "id": 1359}, {"file_name": "310.bmp", "height": 128, "width": 128, "id": 1360}, {"file_name": "1028.bmp", "height": 128, "width": 128, "id": 1361}, {"file_name": "1732.bmp", "height": 128, "width": 128, "id": 1362}, {"file_name": "705.bmp", "height": 128, "width": 128, "id": 1363}, {"file_name": "489.bmp", "height": 128, "width": 128, "id": 1365}, {"file_name": "477.bmp", "height": 128, "width": 128, "id": 1367}, {"file_name": "483.bmp", "height": 128, "width": 128, "id": 1368}, {"file_name": "1486.bmp", "height": 128, "width": 128, "id": 1369}, {"file_name": "765.bmp", "height": 128, "width": 128, "id": 1371}, {"file_name": "394.bmp", "height": 128, "width": 128, "id": 1372}, {"file_name": "637.bmp", "height": 128, "width": 128, "id": 1373}, {"file_name": "321.bmp", "height": 128, "width": 128, "id": 1374}, {"file_name": "517.bmp", "height": 128, "width": 128, "id": 1375}, {"file_name": "803.bmp", "height": 128, "width": 128, "id": 1377}, {"file_name": "282.bmp", "height": 128, "width": 128, "id": 1378}, {"file_name": "1281.bmp", "height": 128, "width": 128, "id": 1379}, {"file_name": "736.bmp", "height": 128, "width": 128, "id": 1380}, {"file_name": "535.bmp", "height": 128, "width": 128, "id": 1381}, {"file_name": "468.bmp", "height": 128, "width": 128, "id": 1382}, {"file_name": "308.bmp", "height": 128, "width": 128, "id": 1383}, {"file_name": "1412.bmp", "height": 128, "width": 128, "id": 1384}, {"file_name": "1002.bmp", "height": 128, "width": 128, "id": 1385}, {"file_name": "545.bmp", "height": 128, "width": 128, "id": 1386}, {"file_name": "1216.bmp", "height": 128, "width": 128, "id": 1387}, {"file_name": "267.bmp", "height": 128, "width": 128, "id": 1388}, {"file_name": "791.bmp", "height": 128, "width": 128, "id": 1389}, {"file_name": "808.bmp", "height": 128, "width": 128, "id": 1390}, {"file_name": "234.bmp", "height": 128, "width": 128, "id": 1392}, {"file_name": "977.bmp", "height": 128, "width": 128, "id": 1393}, {"file_name": "1370.bmp", "height": 128, "width": 128, "id": 1395}, {"file_name": "1231.bmp", "height": 128, "width": 128, "id": 1397}, {"file_name": "1460.bmp", "height": 128, "width": 128, "id": 1398}, {"file_name": "1893.bmp", "height": 128, "width": 128, "id": 1399}, {"file_name": "802.bmp", "height": 128, "width": 128, "id": 1400}, {"file_name": "730.bmp", "height": 128, "width": 128, "id": 1404}, {"file_name": "660.bmp", "height": 128, "width": 128, "id": 1405}, {"file_name": "011.bmp", "height": 128, "width": 128, "id": 1406}, {"file_name": "1714.bmp", "height": 128, "width": 128, "id": 1407}, {"file_name": "1072.bmp", "height": 128, "width": 128, "id": 1408}, {"file_name": "309.bmp", "height": 128, "width": 128, "id": 1409}, {"file_name": "534.bmp", "height": 128, "width": 128, "id": 1410}, {"file_name": "794.bmp", "height": 128, "width": 128, "id": 1411}, {"file_name": "611.bmp", "height": 128, "width": 128, "id": 1412}, {"file_name": "1861.bmp", "height": 128, "width": 128, "id": 1413}, {"file_name": "1195.bmp", "height": 128, "width": 128, "id": 1414}, {"file_name": "1713.bmp", "height": 128, "width": 128, "id": 1415}, {"file_name": "1744.bmp", "height": 128, "width": 128, "id": 1416}, {"file_name": "1707.bmp", "height": 128, "width": 128, "id": 1417}, {"file_name": "1145.bmp", "height": 128, "width": 128, "id": 1418}, {"file_name": "653.bmp", "height": 128, "width": 128, "id": 1419}, {"file_name": "1449.bmp", "height": 128, "width": 128, "id": 1420}, {"file_name": "381.bmp", "height": 128, "width": 128, "id": 1421}, {"file_name": "686.bmp", "height": 128, "width": 128, "id": 1422}, {"file_name": "1675.bmp", "height": 128, "width": 128, "id": 1423}, {"file_name": "1915.bmp", "height": 128, "width": 128, "id": 1424}, {"file_name": "447.bmp", "height": 128, "width": 128, "id": 1425}, {"file_name": "1232.bmp", "height": 128, "width": 128, "id": 1428}, {"file_name": "1095.bmp", "height": 128, "width": 128, "id": 1429}, {"file_name": "1866.bmp", "height": 128, "width": 128, "id": 1430}, {"file_name": "1514.bmp", "height": 128, "width": 128, "id": 1431}, {"file_name": "1790.bmp", "height": 128, "width": 128, "id": 1432}, {"file_name": "099.bmp", "height": 128, "width": 128, "id": 1433}, {"file_name": "755.bmp", "height": 128, "width": 128, "id": 1434}, {"file_name": "1792.bmp", "height": 128, "width": 128, "id": 1436}, {"file_name": "524.bmp", "height": 128, "width": 128, "id": 1437}, {"file_name": "264.bmp", "height": 128, "width": 128, "id": 1438}, {"file_name": "1121.bmp", "height": 128, "width": 128, "id": 1439}, {"file_name": "1434.bmp", "height": 128, "width": 128, "id": 1440}, {"file_name": "1368.bmp", "height": 128, "width": 128, "id": 1441}, {"file_name": "1285.bmp", "height": 128, "width": 128, "id": 1442}, {"file_name": "1398.bmp", "height": 128, "width": 128, "id": 1443}, {"file_name": "1376.bmp", "height": 128, "width": 128, "id": 1444}, {"file_name": "1822.bmp", "height": 128, "width": 128, "id": 1445}, {"file_name": "259.bmp", "height": 128, "width": 128, "id": 1446}, {"file_name": "1681.bmp", "height": 128, "width": 128, "id": 1448}], "annotations": [], "categories": [{"supercategory": "none", "id": 1, "name": "puncta"}]}